{"name":"Test case -Signed-In","id":"stories/Global_Nav/SignedIn.story;Test case -Signed-In","testSteps":[{"number":1,"description":"Given User on home page","duration":5558,"startTime":1516793219159,"screenshots":[{"screenshot":"724fe865361fb5bf5ec3a65ad3a877de296d9772e04acc81dea64370d5894b62.png"}],"result":"SUCCESS","precondition":false,"children":[{"number":2,"description":"Is the home page","duration":5224,"startTime":1516793219169,"screenshots":[{"screenshot":"724fe865361fb5bf5ec3a65ad3a877de296d9772e04acc81dea64370d5894b62.png"}],"result":"SUCCESS","precondition":false}]},{"number":3,"description":"When User Signed In","duration":25173,"startTime":1516793224717,"screenshots":[{"screenshot":"454cc7cdf50d2bc698b6300e497fa27ea328d33952ee1840d381959cf84052d9.png"}],"result":"SUCCESS","precondition":false,"children":[{"number":4,"description":"Is signin","duration":24545,"startTime":1516793225044,"screenshots":[{"screenshot":"454cc7cdf50d2bc698b6300e497fa27ea328d33952ee1840d381959cf84052d9.png"}],"result":"SUCCESS","precondition":false}]},{"number":5,"description":"Then User see the Text \u0027Account\u0027 must be displayed","duration":1279,"startTime":1516793249891,"screenshots":[{"screenshot":"454cc7cdf50d2bc698b6300e497fa27ea328d33952ee1840d381959cf84052d9.png"}],"result":"SUCCESS","precondition":false,"children":[{"number":6,"description":"Expected text: Account","duration":650,"startTime":1516793250202,"screenshots":[{"screenshot":"454cc7cdf50d2bc698b6300e497fa27ea328d33952ee1840d381959cf84052d9.png"}],"result":"SUCCESS","precondition":false}]},{"number":7,"description":"When User Hover Over \u0027Account\u0027","duration":4417,"startTime":1516793251173,"screenshots":[{"screenshot":"0bd6b5e9707ed9f3689707c91abaa2ff8d0567c79f73c63135dbf04f181ad699.png"}],"result":"SUCCESS","precondition":false,"children":[{"number":8,"description":"Hover on signin: Account","duration":3768,"startTime":1516793251483,"screenshots":[{"screenshot":"ee021cc853238c8bd8f005b5c89f53d4efaa9a01b76f238df4a0492197e4100a.png"}],"result":"SUCCESS","precondition":false}]},{"number":9,"description":"Then User see the panel must slide down showing two Account options \u0027Oracle Account\u0027 and \u0027Cloud Account\u0027","duration":1322,"startTime":1516793255590,"screenshots":[{"screenshot":"0bd6b5e9707ed9f3689707c91abaa2ff8d0567c79f73c63135dbf04f181ad699.png"}],"result":"SUCCESS","precondition":false,"children":[{"number":10,"description":"Expected option display: Oracle Account, Cloud Account","duration":693,"startTime":1516793255908,"screenshots":[{"screenshot":"0bd6b5e9707ed9f3689707c91abaa2ff8d0567c79f73c63135dbf04f181ad699.png"}],"result":"SUCCESS","precondition":false}]},{"number":11,"description":"Then User verify Oracle account must have options:\n［|option           |\n|Sign Out         |\n|Account          |\n|Help             |］","duration":2622,"startTime":1516793256913,"screenshots":[{"screenshot":"0bd6b5e9707ed9f3689707c91abaa2ff8d0567c79f73c63135dbf04f181ad699.png"}],"result":"SUCCESS","precondition":false,"children":[{"number":12,"description":"Expected oracle account option: Sign Out","duration":633,"startTime":1516793257247,"screenshots":[{"screenshot":"0bd6b5e9707ed9f3689707c91abaa2ff8d0567c79f73c63135dbf04f181ad699.png"}],"result":"SUCCESS","precondition":false},{"number":13,"description":"Expected oracle account option: Account","duration":645,"startTime":1516793257880,"screenshots":[{"screenshot":"0bd6b5e9707ed9f3689707c91abaa2ff8d0567c79f73c63135dbf04f181ad699.png"}],"result":"SUCCESS","precondition":false},{"number":14,"description":"Expected oracle account option: Help","duration":700,"startTime":1516793258526,"screenshots":[{"screenshot":"0bd6b5e9707ed9f3689707c91abaa2ff8d0567c79f73c63135dbf04f181ad699.png"}],"result":"SUCCESS","precondition":false}]},{"number":15,"description":"Then User verify Cloud account must have only option:\n［|option |\n|Sign In|\n|Sign Up—Free Trial|］","duration":1945,"startTime":1516793259536,"screenshots":[{"screenshot":"0bd6b5e9707ed9f3689707c91abaa2ff8d0567c79f73c63135dbf04f181ad699.png"}],"result":"SUCCESS","precondition":false,"children":[{"number":16,"description":"Expected cloud account option: Sign In","duration":646,"startTime":1516793259847,"screenshots":[{"screenshot":"0bd6b5e9707ed9f3689707c91abaa2ff8d0567c79f73c63135dbf04f181ad699.png"}],"result":"SUCCESS","precondition":false},{"number":17,"description":"Expected cloud account option: Sign Up—Free Trial","duration":649,"startTime":1516793260493,"screenshots":[{"screenshot":"0bd6b5e9707ed9f3689707c91abaa2ff8d0567c79f73c63135dbf04f181ad699.png"}],"result":"SUCCESS","precondition":false}]},{"number":18,"description":"Then User Click on Cloud Account each links:\n［|Option  |Link              |appropriate page        |\n|Account |Sign In           |Oracle Cloud            |\n|Account |Sign Up—Free Trial|Oracle Cloud            |］","duration":38793,"startTime":1516793261482,"screenshots":[{"screenshot":"0bd6b5e9707ed9f3689707c91abaa2ff8d0567c79f73c63135dbf04f181ad699.png"}],"result":"SUCCESS","precondition":false,"children":[{"number":19,"description":"Is page: Account, Sign In, Oracle Cloud","duration":19582,"startTime":1516793261815,"screenshots":[{"screenshot":"0bd6b5e9707ed9f3689707c91abaa2ff8d0567c79f73c63135dbf04f181ad699.png"}],"result":"SUCCESS","precondition":false,"children":[{"number":20,"description":"Page: Account, Sign In, Oracle Cloud","duration":11371,"startTime":1516793269695,"screenshots":[{"screenshot":"43652ec651ab06d2cfaf4f501d4c648704f8e4d7ce3e11b6227a93e38cb36e43.png"},{"screenshot":"f02e17d62b72de36d4bec2c289b7dd2fa5536b4d8f3e717824d67ee4331c5dd0.png"}],"result":"SUCCESS","precondition":false}]},{"number":21,"description":"Is page: Account, Sign Up—Free Trial, Oracle Cloud","duration":18559,"startTime":1516793281397,"screenshots":[{"screenshot":"0bd6b5e9707ed9f3689707c91abaa2ff8d0567c79f73c63135dbf04f181ad699.png"}],"result":"SUCCESS","precondition":false,"children":[{"number":22,"description":"Page: Account, Sign Up—Free Trial, Oracle Cloud","duration":11336,"startTime":1516793288262,"screenshots":[{"screenshot":"353e68b6ae19b27bfee7758afdfdd37b7bec854bb4d85a2615743a3b2f8048fc.png"},{"screenshot":"78553ce0b2226a0c15be1ce5e683d54a37a936360b8f14c649018d9ae4eee4bc.png"}],"result":"SUCCESS","precondition":false}]}]},{"number":23,"description":"Then User Clicks on oracle account each links:\n|Option |Link             |appropriate page         |\n|Account|Help             |About Your Oracle Account|\n|Account|Account          |Update Account           |\n|Account|Sign Out         |Integrated Cloud Applications and Platform Services|","duration":0,"startTime":1516793300276,"screenshots":[{"screenshot":"0bd6b5e9707ed9f3689707c91abaa2ff8d0567c79f73c63135dbf04f181ad699.png"}],"precondition":false,"children":[{"number":24,"description":"Is page: Account, Help, About Your Oracle Account","duration":22605,"startTime":1516793300589,"screenshots":[{"screenshot":"29f9ff33cf2c4e8c3c8707d2c6afcafdb113969d8db6823c8eb1b879423762d4.png"}],"result":"SUCCESS","precondition":false,"children":[{"number":25,"description":"Page: About Your Oracle Account","duration":13848,"startTime":1516793309031,"screenshots":[{"screenshot":"ce528c1a19f8ede71ace47797fb72b14d30f92f9c453d014c055b3418fdc58f0.png"},{"screenshot":"29f9ff33cf2c4e8c3c8707d2c6afcafdb113969d8db6823c8eb1b879423762d4.png"}],"result":"SUCCESS","precondition":false}]},{"number":26,"description":"Is page: Account, Account, Update Account","duration":21538,"startTime":1516793323194,"screenshots":[{"screenshot":"29f9ff33cf2c4e8c3c8707d2c6afcafdb113969d8db6823c8eb1b879423762d4.png"}],"exception":{"errorType":"java.lang.AssertionError","stackTrace":[{"declaringClass":"com.bdd.sample.pages.SignedInPage","methodName":"is_page","fileName":"SignedInPage.java","lineNumber":227},{"declaringClass":"com.bdd.sample.steps.serenity.SignedInSteps","methodName":"page","fileName":"SignedInSteps.java","lineNumber":55},{"declaringClass":"com.bdd.sample.steps.serenity.SignedInSteps","methodName":"is_page","fileName":"SignedInSteps.java","lineNumber":62},{"declaringClass":"com.bdd.sample.steps2.SignedInDefinition","methodName":"UserClickonOracleAccounteachlinks","fileName":"SignedInDefinition.java","lineNumber":78}]},"result":"FAILURE","precondition":false,"children":[{"number":27,"description":"Page: Update Account","duration":9668,"startTime":1516793335064,"screenshots":[{"screenshot":"3def44f2c11241d020fc0b16ea1ffac205f8cefe8d83209d829ae0aa5adbecf6.png"},{"screenshot":"1f04b804deac045dbc618bb7878e4c44c30d5f353010ccf71cc9524a072b3e20.png","htmlSource":"pagesource5077710914498868723.html.txt"}],"exception":{"errorType":"java.lang.AssertionError","stackTrace":[{"declaringClass":"com.bdd.sample.pages.SignedInPage","methodName":"is_page","fileName":"SignedInPage.java","lineNumber":227},{"declaringClass":"com.bdd.sample.steps.serenity.SignedInSteps","methodName":"page","fileName":"SignedInSteps.java","lineNumber":55},{"declaringClass":"com.bdd.sample.steps.serenity.SignedInSteps","methodName":"is_page","fileName":"SignedInSteps.java","lineNumber":62},{"declaringClass":"com.bdd.sample.steps2.SignedInDefinition","methodName":"UserClickonOracleAccounteachlinks","fileName":"SignedInDefinition.java","lineNumber":78}]},"result":"FAILURE","precondition":false}]}]}],"userStory":{"id":"SignedIn","storyName":"Signed in","path":"stories/Global_Nav/SignedIn.story","narrative":"In order to check Functionality\nAs a Tester\nI want to verify Global Nav application\n\n\neta:@skip","type":"story"},"featureTag":{"name":"Global  nav/Signed in","type":"story"},"title":"Test case -Signed-In","tags":[{"name":"chrome","type":"browser"},{"name":"chrome","type":"context"},{"name":"Global nav","type":"feature"},{"name":"Global nav/Signed in","type":"story"}],"startTime":1516793219158,"duration":125587,"testFailureCause":{"errorType":"java.lang.AssertionError","stackTrace":[{"declaringClass":"com.bdd.sample.pages.SignedInPage","methodName":"is_page","fileName":"SignedInPage.java","lineNumber":227},{"declaringClass":"com.bdd.sample.steps.serenity.SignedInSteps","methodName":"page","fileName":"SignedInSteps.java","lineNumber":55},{"declaringClass":"com.bdd.sample.steps.serenity.SignedInSteps","methodName":"is_page","fileName":"SignedInSteps.java","lineNumber":62},{"declaringClass":"com.bdd.sample.steps2.SignedInDefinition","methodName":"UserClickonOracleAccounteachlinks","fileName":"SignedInDefinition.java","lineNumber":78}]},"testFailureClassname":"java.lang.AssertionError","testFailureSummary":"FAILURE;java.lang.AssertionError;null;SignedInPage.java","projectKey":"","annotatedResult":"FAILURE","sessionId":"48b32b38e7011d2a76d1585c6109c1cd","driver":"chrome","context":"chrome","manual":false,"testSource":"JBehave","result":"FAILURE"}