{"name":"Test case -Not Signed-In","id":"stories/Global_Nav/NotSignedIn.story;Test case -Not Signed-In","testSteps":[{"number":1,"description":"Given User on home page","duration":8707,"startTime":1517913161527,"screenshots":[{"screenshot":"9f0eae794c9d06c18ac41683fa9922af6e1d2ba52986532a1bef0ae9522dc196.png"}],"result":"SUCCESS","precondition":false,"children":[{"number":2,"description":"Is the home page","duration":8447,"startTime":1517913161532,"screenshots":[{"screenshot":"9f0eae794c9d06c18ac41683fa9922af6e1d2ba52986532a1bef0ae9522dc196.png"}],"result":"SUCCESS","precondition":false}]},{"number":3,"description":"When User Not signed In","duration":1270,"startTime":1517913170234,"screenshots":[{"screenshot":"9f0eae794c9d06c18ac41683fa9922af6e1d2ba52986532a1bef0ae9522dc196.png"}],"result":"SUCCESS","precondition":false,"children":[{"number":4,"description":"Is not signin","duration":667,"startTime":1517913170487,"screenshots":[{"screenshot":"9f0eae794c9d06c18ac41683fa9922af6e1d2ba52986532a1bef0ae9522dc196.png"}],"result":"SUCCESS","precondition":false}]},{"number":5,"description":"Then User see the text \u0027Sign In\u0027 must be displayed","duration":10969,"startTime":1517913171504,"screenshots":[{"screenshot":"9f0eae794c9d06c18ac41683fa9922af6e1d2ba52986532a1bef0ae9522dc196.png"}],"result":"SUCCESS","precondition":false,"children":[{"number":6,"description":"Expected text: Sign In","duration":10501,"startTime":1517913171742,"screenshots":[{"screenshot":"9f0eae794c9d06c18ac41683fa9922af6e1d2ba52986532a1bef0ae9522dc196.png"}],"result":"SUCCESS","precondition":false}]},{"number":7,"description":"When User Hover over \u0027Sign In\u0027","duration":2860,"startTime":1517913182474,"screenshots":[{"screenshot":"a5c7834e35017571c007444ed51ba5b432f8455341bed36b9604715f32bf0d63.png"}],"result":"SUCCESS","precondition":false,"children":[{"number":8,"description":"Hover on signin: Sign In","duration":2117,"startTime":1517913182717,"screenshots":[{"screenshot":"e76baaeb0b9a5e75624ceb8918cd8b9a0637f9872aca7713468e57c51c3d99c7.png"}],"result":"SUCCESS","precondition":false}]},{"number":9,"description":"Then User see the panel must slide down showing two account options \u0027Oracle Account\u0027 and \u0027Cloud Account\u0027","duration":1492,"startTime":1517913185335,"screenshots":[{"screenshot":"5f27442a92503624eec51ba21f1425c0553dec997717c4faa66496c23abdb5c3.png"}],"result":"SUCCESS","precondition":false,"children":[{"number":10,"description":"Expected option display: Oracle Account, Cloud Account","duration":745,"startTime":1517913185843,"screenshots":[{"screenshot":"5f27442a92503624eec51ba21f1425c0553dec997717c4faa66496c23abdb5c3.png"}],"result":"SUCCESS","precondition":false}]},{"number":11,"description":"Then User verify Oracle Account must have options:\n［|option           |\n|Sign in          |\n|Create an account|\n|Help             |］","duration":2061,"startTime":1517913186831,"screenshots":[{"screenshot":"5f27442a92503624eec51ba21f1425c0553dec997717c4faa66496c23abdb5c3.png"}],"result":"SUCCESS","precondition":false,"children":[{"number":12,"description":"Expected oracle account option: Sign in","duration":510,"startTime":1517913187076,"screenshots":[{"screenshot":"5f27442a92503624eec51ba21f1425c0553dec997717c4faa66496c23abdb5c3.png"}],"result":"SUCCESS","precondition":false},{"number":13,"description":"Expected oracle account option: Create an account","duration":554,"startTime":1517913187586,"screenshots":[{"screenshot":"5f27442a92503624eec51ba21f1425c0553dec997717c4faa66496c23abdb5c3.png"}],"result":"SUCCESS","precondition":false},{"number":14,"description":"Expected oracle account option: Help","duration":515,"startTime":1517913188140,"screenshots":[{"screenshot":"5f27442a92503624eec51ba21f1425c0553dec997717c4faa66496c23abdb5c3.png"}],"result":"SUCCESS","precondition":false}]},{"number":15,"description":"Then User verify Cloud Account must have only option:\n［|option |\n|Sign In|\n|Sign Up—Free Trial|］","duration":1563,"startTime":1517913188893,"screenshots":[{"screenshot":"5f27442a92503624eec51ba21f1425c0553dec997717c4faa66496c23abdb5c3.png"}],"result":"SUCCESS","precondition":false,"children":[{"number":16,"description":"Expected cloud account option: Sign In","duration":552,"startTime":1517913189145,"screenshots":[{"screenshot":"5f27442a92503624eec51ba21f1425c0553dec997717c4faa66496c23abdb5c3.png"}],"result":"SUCCESS","precondition":false},{"number":17,"description":"Expected cloud account option: Sign Up—Free Trial","duration":514,"startTime":1517913189697,"screenshots":[{"screenshot":"5f27442a92503624eec51ba21f1425c0553dec997717c4faa66496c23abdb5c3.png"}],"result":"SUCCESS","precondition":false}]},{"number":18,"description":"Then User Click on Cloud Account each links:\n［|Option  |Link              |appropriate page        |\n|Sign In |Sign In           |Oracle Cloud            |\n|Sign In |Sign Up—Free Trial|Oracle Cloud            |］","duration":32870,"startTime":1517913190457,"screenshots":[{"screenshot":"5f27442a92503624eec51ba21f1425c0553dec997717c4faa66496c23abdb5c3.png"}],"result":"SUCCESS","precondition":false,"children":[{"number":19,"description":"Is page: Sign In, Sign In, Oracle Cloud","duration":18394,"startTime":1517913190701,"screenshots":[{"screenshot":"5f27442a92503624eec51ba21f1425c0553dec997717c4faa66496c23abdb5c3.png"}],"result":"SUCCESS","precondition":false,"children":[{"number":20,"description":"Page: Sign In, Sign In, Oracle Cloud","duration":14788,"startTime":1517913194049,"screenshots":[{"screenshot":"b661b9dd94c5940b70f6dae6419168d175c2f390a98a7eedba18cb1079d17209.png"},{"screenshot":"5f27442a92503624eec51ba21f1425c0553dec997717c4faa66496c23abdb5c3.png"}],"result":"SUCCESS","precondition":false}]},{"number":21,"description":"Is page: Sign In, Sign Up—Free Trial, Oracle Cloud","duration":13990,"startTime":1517913209096,"screenshots":[{"screenshot":"5f27442a92503624eec51ba21f1425c0553dec997717c4faa66496c23abdb5c3.png"}],"result":"SUCCESS","precondition":false,"children":[{"number":22,"description":"Page: Sign In, Sign Up—Free Trial, Oracle Cloud","duration":10407,"startTime":1517913212428,"screenshots":[{"screenshot":"e9ab837634b9368e7835c4e995c57328b8b7ba8c0da46a045ad222cf1b7b27d6.png"},{"screenshot":"5f27442a92503624eec51ba21f1425c0553dec997717c4faa66496c23abdb5c3.png"}],"result":"SUCCESS","precondition":false}]}]},{"number":23,"description":"Then User Click on Oracle Account each links:\n［|Option |Link             |appropriate page         |\n|Sign In|Help             |About Your Oracle Account|\n|Sign In|Create an account|Create Account           |\n|Sign In|Sign in          |Single Sign On - Login   |］","duration":81841,"startTime":1517913223329,"screenshots":[{"screenshot":"b6cf303a1bc593be4bfe7aa891ee57c47ef080cefd53f04f28481dd3f0c4cec7.png"}],"result":"SUCCESS","precondition":false,"children":[{"number":24,"description":"Is page: Sign In, Help, About Your Oracle Account","duration":12888,"startTime":1517913223574,"screenshots":[{"screenshot":"9231e9eccbfc54245ae759bb8b345d9c9ff10e4264917bdb0a2a407e2e3e4f7c.png"}],"result":"SUCCESS","precondition":false},{"number":25,"description":"Page: Sign In, Help, About Your Oracle Account","duration":10386,"startTime":1517913238463,"screenshots":[{"screenshot":"9231e9eccbfc54245ae759bb8b345d9c9ff10e4264917bdb0a2a407e2e3e4f7c.png"},{"screenshot":"5f27442a92503624eec51ba21f1425c0553dec997717c4faa66496c23abdb5c3.png"}],"result":"SUCCESS","precondition":false},{"number":26,"description":"Is page: Sign In, Create an account, Create Account","duration":12491,"startTime":1517913248849,"screenshots":[{"screenshot":"bf2dbe22d52b272a4b34720dd4db8a371244c11a3bcaf7168bb9671d3e6f2b4c.png"}],"result":"SUCCESS","precondition":false},{"number":27,"description":"Page: Sign In, Create an account, Create Account","duration":10654,"startTime":1517913263341,"screenshots":[{"screenshot":"bf2dbe22d52b272a4b34720dd4db8a371244c11a3bcaf7168bb9671d3e6f2b4c.png"},{"screenshot":"5f27442a92503624eec51ba21f1425c0553dec997717c4faa66496c23abdb5c3.png"}],"result":"SUCCESS","precondition":false},{"number":28,"description":"Is page: Sign In, Sign in, Single Sign On - Login","duration":12466,"startTime":1517913273995,"screenshots":[{"screenshot":"b163890a2e0c41e0693afe8e1a500237aed627f08c7571924dc60cdc78c66ddb.png"}],"result":"SUCCESS","precondition":false},{"number":29,"description":"Page: Sign In, Sign in, Single Sign On - Login","duration":16434,"startTime":1517913288462,"screenshots":[{"screenshot":"b163890a2e0c41e0693afe8e1a500237aed627f08c7571924dc60cdc78c66ddb.png"},{"screenshot":"b6cf303a1bc593be4bfe7aa891ee57c47ef080cefd53f04f28481dd3f0c4cec7.png"}],"result":"SUCCESS","precondition":false}]}],"userStory":{"id":"NotSignedIn","storyName":"Not signed in","path":"stories/Global_Nav/NotSignedIn.story","narrative":"In order to check Functionality\nAs a n Tester\nI want to verify Global Nav application\neta:@skip","type":"story"},"featureTag":{"name":"Global  nav/Not signed in","type":"story"},"title":"Test case -Not Signed-In","tags":[{"name":"Global nav/Not signed in","type":"story"},{"name":"firefox","type":"browser"},{"name":"firefox","type":"context"},{"name":"Global nav","type":"feature"}],"startTime":1517913161526,"duration":143648,"projectKey":"","sessionId":"dcf06697-6502-4479-a7b0-f001ff1f7b22","driver":"firefox","context":"firefox","manual":false,"testSource":"JBehave","result":"SUCCESS"}